g2sd/__init__.py
g2sd/g2sd.py
g2sd-1.3.1.dist-info/LICENSE
g2sd-1.3.1.dist-info/METADATA
g2sd-1.3.1.dist-info/WHEEL
g2sd-1.3.1.dist-info/entry_points.txt
g2sd-1.3.1.dist-info/top_level.txt
g2sd-1.3.1.dist-info/zip-safe
g2sd-1.3.1.dist-info/RECORD
