Metadata-Version: 2.1
Name: g2sd
Version: 1.3.1
Summary: Convert GRUB menu entries into Systemd-boot boot loaders.
Home-page: https://github.com/thismachinechills/grub2systemd
Author: thismachinechills (Alex)
Author-email: UNKNOWN
License: AGPL 3.0
Keywords: grub2,grub,systemd,systemd-boot,menuentry,efi,efiboot,uefi
Platform: UNKNOWN
Requires-Dist: click
